axio2zarr/__init__.py
axio2zarr/array.py
axio2zarr-0.2.6.dist-info/METADATA
axio2zarr-0.2.6.dist-info/WHEEL
axio2zarr-0.2.6.dist-info/entry_points.txt
axio2zarr-0.2.6.dist-info/top_level.txt
axio2zarr-0.2.6.dist-info/RECORD
