Metadata-Version: 2.1
Name: axio2zarr
Version: 0.2.6
Summary: AXIOSCAN to Zarr conversion
Home-page: https://gitlab.developers.cam.ac.uk/astronomy/camcead/imaxt/axio2zarr
Author: "Eduardo Gonzalez Solares"
Author-email: "E.GonzalezSolares@ast.cam.ac.uk"
Project-URL: Bug Tracker, https://gitlab.developers.cam.ac.uk/astronomy/camcead/imaxt/axio2zarr/-/issues
Classifier: Programming Language :: Python :: 3
Classifier: License :: OSI Approved :: MIT License
Classifier: Operating System :: OS Independent
Requires-Python: >=3.9
Requires-Dist: aicspylibczi
Requires-Dist: click
Requires-Dist: dask
Requires-Dist: distributed
Requires-Dist: numpy
Requires-Dist: xarray
Requires-Dist: zarr
